{
  "id": "1/52",
  "decrypted": [
    " .  .  .  .  .  P  .  .  .  .  .  .  .  . ",
    " .  .  .  .  .  R  .  .  .  .  .  .  .  . ",
    " .  .  .  .  .  E  .  .  .  .  .  .  .  . ",
    " .  .  .  .  .  D  .  .  .  .  .  .  .  . ",
    " .  .  .  .  M  I  T  H  R  A  I  C  .  . ",
    " .  .  .  .  .  V  .  .  .  .  .  .  .  . ",
    " .  .  .  .  .  I  .  .  .  V  .  R  .  . ",
    " .  .  .  .  .  D  .  H  .  E  .  E  .  . ",
    " .  .  .  .  .  E  .  O  .  S  .  S  .  . ",
    " .  .  .  .  S  .  .  P  .  I  .  U  .  . ",
    " .  .  .  .  P  .  .  E  .  C  .  L  .  . ",
    " R  U  M  N  E  Y  .  L  .  O  .  T  .  . ",
    " .  .  .  .  C  .  .  E  .  S  .  L  .  E ",
    " .  S  E  M  I  H  O  S  T  I  L  E  L  Y ",
    " .  .  .  .  A  .  .  S  .  G  .  S  .  R ",
    " .  .  .  .  L  .  .  N  .  M  .  S  .  A ",
    " N  O  N  O  I  C  .  E  .  O  .  L  .  N ",
    " .  .  .  .  T  .  .  S  .  I  .  Y  .  T ",
    " .  .  .  .  Y  .  .  S  .  D  .  .  .  . "
  ],
  "encrypted": [
    " 0  0  0  0  0 15  0  0  0  0  0  0  0  0 ",
    " 0  0  0  0  0  9  0  0  0  0  0  0  0  0 ",
    " 0  0  0  0  0 13  0  0  0  0  0  0  0  0 ",
    " 0  0  0  0  0 24  0  0  0  0  0  0  0  0 ",
    " 0  0  0  0 16  1  5 22  9 26  1 12  0  0 ",
    " 0  0  0  0  0 25  0  0  0  0  0  0  0  0 ",
    " 0  0  0  0  0  1  0  0  0 25  0  9  0  0 ",
    " 0  0  0  0  0 24  0 22  0 13  0 13  0  0 ",
    " 0  0  0  0  0 13  0 20  0 21  0 21  0  0 ",
    " 0  0  0  0 21  0  0 15  0  1  0  3  0  0 ",
    " 0  0  0  0 15  0  0 13  0 12  0 14  0  0 ",
    " 9  3 16  7 13 17  0 14  0 20  0  5  0  0 ",
    " 0  0  0  0 12  0  0 13  0 21  0 14  0 13 ",
    " 0 21 13 16  1 22 20 21  5  1 14 13 14 17 ",
    " 0  0  0  0 26  0  0 21  0 18  0 21  0  9 ",
    " 0  0  0  0 14  0  0  7  0 16  0 21  0 26 ",
    " 7 20  7 20  1 12  0 13  0 20  0 14  0  7 ",
    " 0  0  0  0  5  0  0 21  0  1  0 17  0  5 ",
    " 0  0  0  0 17  0  0 21  0 24  0  0  0  0 "
  ],
  "key": [
    {
      "letter": "S",
      "number": 21
    },
    {
      "letter": "L",
      "number": 14
    },
    {
      "letter": "A",
      "number": 26
    },
    {
      "letter": "B",
      "number": 8
    },
    {
      "letter": "S",
      "number": 21
    }
  ],
  "rows": 19,
  "cols": 14
}